Workbook

Sheet Leia-me
A1: SyncSheet — Sistema de Gestão Financeira
A2: Sua planilha, seu sistema, seus dados.
A4: 🚀 COMO USAR O SEU SYNCSHEET
A6: 1. Acesse o sistema online com o LINK ENVIADO no seu e-mail/mensagem do Mercado Livre.
A7: 2. Faça o upload deste arquivo Excel no sistema.
A8: 3. Use a interface visual para cadastrar clientes, produtos, vendas, contas e mais.
A9: 4. Quando terminar, clique em 'Baixar Planilha Atualizada'.
A10: 5. Salve o arquivo no seu computador — agora ele está atualizado com tudo que você fez.
A12: 📊 O QUE VOCÊ ENCONTRA NESTE ARQUIVO
A14: • Painel — KPIs financeiros, vendas e gestão num único lugar
A15: • Clientes — Cadastro completo com canais de venda
A16: • Produtos — Catálogo com cálculo automático de margem e estoque
... A50: Este arquivo é licenciado individualmente. A distribuição não autorizada é proibida.

Sheet Painel
A1: SyncSheet — Sistema de Gestão Financeira
A2: Painel — Visão Geral
A3: KPIs financeiros, vendas e estoque em tempo real
A5: 📊 FINANCEIRO
A6: RECEITA BRUTA (ANO) | C6: LUCRO BRUTO (ANO) | E6: RESULTADO LÍQUIDO | G6: MARGEM LÍQUIDA
A7: =DRE!O11 | C7: =DRE!O21 | E7: =DRE!O43 | G7: =DRE!O45
A9: 🛒 VENDAS
A10: TOTAL DE VENDAS | C10: FATURAMENTO (PAGAS) | E10: TICKET MÉDIO | G10: CLIENTES CADASTRADOS
A11: =COUNTA(Vendas!B5:B200) | C11: =SUMIF(Vendas!K5:K200,"Pago",Vendas!I5:I200) | E11: =IFERROR(SUMIF(Vendas!K5:K200,"Pago",Vendas!I5:I200)/COUNTIF(Vendas!K5:K200,"Pago"),0) | G11: =COUNTA(Clientes!A5:A200)
A13: 📦 ESTOQUE
A14: TOTAL DE PRODUTOS | C14: VALOR EM ESTOQUE | E14: PRECISAM REPOR | G14: SEM ESTOQUE
A15: =COUNTA(Produtos!A5:A200) | C15: =SUM(Produtos!J5:J200) | E15: =COUNTIF(Produtos!K5:K200,"REPOR") | G15: =COUNTIF(Produtos!K5:K200,"SEM ESTOQUE")
A17: 💼 POSIÇÃO DE CONTAS
A18: Descrição | E18: Valor
A19: A Receber — Pendente | E19: =SUMIF('Contas a Receber'!H5:H200,"Pendente",'Contas a Receber'!E5:E200)-SUMIF('Contas a Receber'!H5:H200,"Pendente",'Contas a Receber'!F5:F200)
A20: A Receber — Recebido | E20: =SUMIF('Contas a Receber'!H5:H200,"Recebido",'Contas a Receber'!F5:F200)
A21: A Pagar — Pendente | E21: =SUMIF('Contas a Pagar'!H5:H200,"Pendente",'Contas a Pagar'!E5:E200)-SUMIF('Contas a Pagar'!H5:H200,"Pendente",'Contas a Pagar'!F5:F200)
A22: A Pagar — Pago | E22: =SUMIF('Contas a Pagar'!H5:H200,"Pago",'Contas a Pagar'!F5:F200)
A23: Saldo Líquido | E23: =(SUMIF('Contas a Receber'!H5:H200,"Pendente",'Contas a Receber'!E5:E200)-SUMIF('Contas a Receber'!H5:H200,"Pendente",'Contas a Receber'!F5:F200))-(SUMIF('Contas a Pagar'!H5:H200,"Pendente",'Contas a Pagar'!E5:E200)-SUMIF('Contas a Pagar'!H5:H200,"Pendente",'Contas a Pagar'!F5:F200))

Sheet Clientes
A1: SyncSheet — Sistema de Gestão Financeira
A2: Clientes
A3: Cadastro de clientes e canais de venda
A4: Código | B4: Nome / Razão Social | C4: CPF/CNPJ | D4: E-mail | E4: Telefone | F4: Cidade | G4: Estado | H4: Canal de Venda | I4: Data Cadastro | J4: Observações
A5: CLI0001 | B5: luis henrique | C5: 5151561564151 | D5: smkm@jjnjk | E5: 16545545482 | F5: lusi | G5: AL | H5: Instagram | I5: 46156.625
A6: CLI0002 | B6: joazinho | C6: 265421515455 | D6: fsd@dff | E6: 16554564584 | F6: duda | G6: BA | H6: WhatsApp | I6: 46156.625 | J6: fs

Sheet Produtos
A1: SyncSheet — Sistema de Gestão Financeira
A2: Produtos
A3: Cadastro de produtos com cálculo automático de estoque e margem
A4: SKU | B4: Produto | C4: Categoria | D4: Unidade | E4: Preço Custo | F4: Preço Venda | G4: Margem % | H4: Estoque Mín. | I4: Estoque Atual | J4: Valor em Estoque | K4: Status | L4: Observações
A5: PROD0001 | B5: camiseta | C5: roupa | D5: UN | E5: 11 | F5: 49.97 | H5: 0
A6: PROD0002 | B6: Moletom | C6: roupas | D6: UN | E6: 30 | F6: 79.98 | H6: 0

Sheet Movimentações
A1: SyncSheet — Sistema de Gestão Financeira
A2: Movimentações de Entrada
A3: Compras de fornecedores com cálculo automático de custo total
A4: Data | B4: SKU | C4: Produto | D4: Fornecedor | E4: Nota Fiscal | F4: Quantidade | G4: Custo Unit. | H4: Custo Total
A5: 46156.625 | B5: PROD0001 | C5: camiseta | D5: textil | E5: 1 | F5: 100 | G5: 11
A6: 46156.625 | B6: PROD0002 | C6: Moletom | D6: textil | E6: 2 | F6: 200 | G6: 30
A7: 46156.625 | B7: PROD0002 | C7: Moletom | D7: textil | E7: 3 | F7: 500 | G7: 30

Sheet Vendas
A1: SyncSheet — Sistema de Gestão Financeira
A2: Vendas
A3: Registro de vendas com cálculo automático de cliente, preço e total
A4: Data | B4: Nº Venda | C4: Cód. Cliente | D4: SKU Produto | E4: Cliente | F4: Quantidade | G4: Preço Unit. | H4: Desconto % | I4: Venda Total | J4: Forma Pgto | K4: Status
A5: 46156.625 | B5: V0001 | C5: CLI0001 | D5: PROD0001 | F5: 10 | H5: 0 | J5: Pix | K5: Pago
A6: 46156.625 | B6: V0002 | C6: CLI0002 | D6: PROD0002 | F6: 100 | H6: 10 | J6: Pix | K6: Pendente

Sheet Fluxo de Caixa
A1: SyncSheet — Sistema de Gestão Financeira
A2: Fluxo de Caixa
A3: Controle de entradas e saídas de caixa do mês
A4: SALDO INICIAL DO MÊS | D4: 0
A6: ENTRADAS
A7: Data | B7: Descrição | C7: Categoria | D7: Cliente / Fornecedor | E7: Forma Pgto | F7: Valor | G7: Status | H7: Observações
A8: 46156.625 | B8: Venda V0001 | C8: R01 | D8: luis henrique | E8: Pix | F8: 499.7 | G8: Confirmado | H8: Auto: venda V0001
A9: 46156.625 | B9: Venda V0002 | C9: R01 | D9: joazinho | E9: Pix | F9: 7198.2 | G9: Confirmado | H9: Auto: Venda V0002
A38: TOTAL ENTRADAS | F38: =SUM(F8:F37)
A40: SAÍDAS
A41: Data | B41: Descrição | C41: Categoria | D41: Cliente / Fornecedor | E41: Forma Pgto | F41: Valor | G41: Status | H41: Observações
A42: 46156.625 | B42: Compra camiseta (NF 1) | C42: D01 | D42: textil | F42: 1100 | G42: Confirmado | H42: Auto: entrada de estoque
A43: 46156.625 | B43: Compra Moletom (NF 3) | C43: D01 | D43: textil | E43: Pix | F43: 15000 | G43: Confirmado | H43: Auto: Compra Moletom (NF 3)
A72: TOTAL SAÍDAS | F72: =SUM(F42:F71)
A75: SALDO FINAL DO MÊS | F75: =D4+F38-F72

Sheet Contas a Pagar
A1: SyncSheet — Sistema de Gestão Financeira
A2: Contas a Pagar
A3: Compromissos financeiros com fornecedores e prestadores
A4: Vencimento | B4: Descrição | C4: Categoria | D4: Fornecedor | E4: Valor | F4: Valor Pago | G4: Data Pgto | H4: Status | I4: Observações
A5: 46167.625 | B5: Compra Moletom (NF 3) | C5: D01 | D5: textil | E5: 15000 | F5: 15000 | G5: 46156.625 | H5: Pago | I5: Auto: entrada de estoque

Sheet Contas a Receber
A1: SyncSheet — Sistema de Gestão Financeira
A2: Contas a Receber
A3: Recebíveis pendentes de clientes e parceiros
A4: Vencimento | B4: Descrição | C4: Categoria | D4: Cliente | E4: Valor | F4: Valor Recebido | G4: Data Recebimento | H4: Status | I4: Observações
A5: 46186.625 | B5: Venda V0002 | C5: R01 | D5: joazinho | E5: 7198.2 | F5: 7198.2 | G5: 46156.625 | H5: Recebido | I5: Auto: venda V0002

Sheet DRE
A1: SyncSheet — Sistema de Gestão Financeira
A2: DRE — Demonstração do Resultado
A3: Análise mensal e anual do resultado financeiro
A4: Conta | B4: Descrição | C4: Janeiro | D4: Fevereiro | E4: Março | F4: Abril | G4: Maio | H4: Junho | I4: Julho | J4: Agosto | K4: Setembro | L4: Outubro | M4: Novembro | N4: Dezembro | O4: Total Anual
A5: 1. | B5: RECEITA BRUTA
A6: 1.1 | B6: Vendas de Produtos | C6: 0 | D6: 0 | E6: 0 | F6: 0 | G6: 499.7 | H6: 0 | I6: 0 | J6: 0 | K6: 0 | L6: 0 | M6: 0 | N6: 0 | O6: =SUM(C6:N6)
A7: 1.2 | B7: Vendas de Serviços | C7: 0 | D7: 0 | E7: 0 | F7: 0 | G7: 0 | H7: 0 | I7: 0 | J7: 0 | K7: 0 | L7: 0 | M7: 0 | N7: 0 | O7: =SUM(C7:N7)
A8: 1.3 | B8: Cursos e Infoprodutos | C8: 0 | D8: 0 | E8: 0 | F8: 0 | G8: 0 | H8: 0 | I8: 0 | J8: 0 | K8: 0 | L8: 0 | M8: 0 | N8: 0 | O8: =SUM(C8:N8)
A9: 1.4 | B9: Assinaturas / Recorrência | C9: 0 | D9: 0 | E9: 0 | F9: 0 | G9: 0 | H9: 0 | I9: 0 | J9: 0 | K9: 0 | L9: 0 | M9: 0 | N9: 0 | O9: =SUM(C9:N9)
A10: 1.5 | B10: Outras Receitas | C10: 0 | D10: 0 | E10: 0 | F10: 0 | G10: 0 | H10: 0 | I10: 0 | J10: 0 | K10: 0 | L10: 0 | M10: 0 | N10: 0 | O10: =SUM(C10:N10)
A11: (=) | B11: RECEITA BRUTA TOTAL | C11: =SUM(C6:C10) | D11: =SUM(D6:D10) | E11: =SUM(E6:E10) | F11: =SUM(F6:F10) | G11: =SUM(G6:G10) | H11: =SUM(H6:H10) | I11: =SUM(I6:I10) | J11: =SUM(J6:J10) | ... N11: =SUM(N6:N10) | O11: =SUM(C11:N11)
A13: 2. | B13: DEDUÇÕES
A14: 2.1 | B14: Impostos sobre Vendas | C14: 0 | D14: 0 | E14: 0 | F14: 0 | G14: 0 | H14: 0 | I14: 0 | J14: 0 | K14: 0 | L14: 0 | M14: 0 | N14: 0 | O14: =SUM(C14:N14)
A15: 2.2 | B15: Devoluções e Cancelamentos | C15: 0 | D15: 0 | E15: 0 | F15: 0 | G15: 0 | H15: 0 | I15: 0 | J15: 0 | K15: 0 | L15: 0 | M15: 0 | N15: 0 | O15: =SUM(C15:N15)
A16: (=) | B16: RECEITA LÍQUIDA | C16: =C11-C14-C15 | D16: =D11-D14-D15 | E16: =E11-E14-E15 | F16: =F11-F14-F15 | G16: =G11-G14-G15 | H16: =H11-H14-H15 | I16: =I11-I14-I15 | J16: =J11-J14-J15 | ... N16: =N11-N14-N15 | O16: =SUM(C16:N16)
A18: 3. | B18: CUSTOS
A19: 3.1 | B19: CMV (Custo da Mercadoria Vendida) | C19: 0 | D19: 0 | E19: 0 | F19: 0 | G19: 1100 | H19: 0 | I19: 0 | J19: 0 | K19: 0 | L19: 0 | M19: 0 | N19: 0 | O19: =SUM(C19:N19)
A20: 3.2 | B20: Custo de Serviço | C20: 0 | D20: 0 | E20: 0 | F20: 0 | G20: 0 | H20: 0 | I20: 0 | J20: 0 | K20: 0 | L20: 0 | M20: 0 | N20: 0 | O20: =SUM(C20:N20)
A21: (=) | B21: LUCRO BRUTO | C21: =C16-C19-C20 | D21: =D16-D19-D20 | E21: =E16-E19-E20 | F21: =F16-F19-F20 | G21: =G16-G19-G20 | H21: =H16-H19-H20 | I21: =I16-I19-I20 | J21: =J16-J19-J20 | ... N21: =N16-N19-N20 | O21: =SUM(C21:N21)
A23: 4. | B23: DESPESAS OPERACIONAIS
A24: 4.1 | B24: Salários e Encargos | C24: 0 | D24: 0 | E24: 0 | F24: 0 | G24: 0 | H24: 0 | I24: 0 | J24: 0 | K24: 0 | L24: 0 | M24: 0 | N24: 0 | O24: =SUM(C24:N24)
A25: 4.2 | B25: Aluguel | C25: 0 | D25: 0 | E25: 0 | F25: 0 | G25: 0 | H25: 0 | I25: 0 | J25: 0 | K25: 0 | L25: 0 | M25: 0 | N25: 0 | O25: =SUM(C25:N25)
A26: 4.3 | B26: Marketing e Publicidade | C26: 0 | D26: 0 | E26: 0 | F26: 0 | G26: 0 | H26: 0 | I26: 0 | J26: 0 | K26: 0 | L26: 0 | M26: 0 | N26: 0 | O26: =SUM(C26:N26)
A27: 4.4 | B27: Ferramentas / Software | C27: 0 | D27: 0 | E27: 0 | F27: 0 | G27: 0 | H27: 0 | I27: 0 | J27: 0 | K27: 0 | L27: 0 | M27: 0 | N27: 0 | O27: =SUM(C27:N27)
A28: 4.5 | B28: Contabilidade | C28: 0 | D28: 0 | E28: 0 | F28: 0 | G28: 0 | H28: 0 | I28: 0 | J28: 0 | K28: 0 | L28: 0 | M28: 0 | N28: 0 | O28: =SUM(C28:N28)
A29: 4.6 | B29: Telefone / Internet | C29: 0 | D29: 0 | E29: 0 | F29: 0 | G29: 0 | H29: 0 | I29: 0 | J29: 0 | K29: 0 | L29: 0 | M29: 0 | N29: 0 | O29: =SUM(C29:N29)
A30: 4.7 | B30: Terceirizados | C30: 0 | D30: 0 | E30: 0 | F30: 0 | G30: 0 | H30: 0 | I30: 0 | J30: 0 | K30: 0 | L30: 0 | M30: 0 | N30: 0 | O30: =SUM(C30:N30)
A31: 4.8 | B31: Material de Consumo | C31: 0 | D31: 0 | E31: 0 | F31: 0 | G31: 0 | H31: 0 | I31: 0 | J31: 0 | K31: 0 | L31: 0 | M31: 0 | N31: 0 | O31: =SUM(C31:N31)
A32: 4.9 | B32: Outras Despesas | C32: 0 | D32: 0 | E32: 0 | F32: 0 | G32: 0 | H32: 0 | I32: 0 | J32: 0 | K32: 0 | L32: 0 | M32: 0 | N32: 0 | O32: =SUM(C32:N32)
A33: (=) | B33: TOTAL DESPESAS OPERACIONAIS | C33: =SUM(C24:C32) | D33: =SUM(D24:D32) | E33: =SUM(E24:E32) | F33: =SUM(F24:F32) | G33: =SUM(G24:G32) | H33: =SUM(H24:H32) | I33: =SUM(I24:I32) | J33: =SUM(J24:J32) | ... N33: =SUM(N24:N32) | O33: =SUM(C33:N33)
A35: (=) | B35: RESULTADO OPERACIONAL | C35: =C21-C33 | D35: =D21-D33 | E35: =E21-E33 | F35: =F21-F33 | G35: =G21-G33 | H35: =H21-H33 | I35: =I21-I33 | J35: =J21-J33 | ... N35: =N21-N33 | O35: =SUM(C35:N35)
A37: 5. | B37: RESULTADO NÃO OPERACIONAL
A38: 5.1 | B38: Receitas Financeiras | C38: 0 | D38: 0 | E38: 0 | F38: 0 | G38: 0 | H38: 0 | I38: 0 | J38: 0 | K38: 0 | L38: 0 | M38: 0 | N38: 0 | O38: =SUM(C38:N38)
A39: 5.2 | B39: Despesas Financeiras | C39: 0 | D39: 0 | E39: 0 | F39: 0 | G39: 0 | H39: 0 | I39: 0 | J39: 0 | K39: 0 | L39: 0 | M39: 0 | N39: 0 | O39: =SUM(C39:N39)
A40: (=) | B40: RESULTADO FINANCEIRO | C40: =C38-C39 | D40: =D38-D39 | E40: =E38-E39 | F40: =F38-F39 | G40: =G38-G39 | H40: =H38-H39 | I40: =I38-I39 | J40: =J38-J39 | ... N40: =N38-N39 | O40: =SUM(C40:N40)
A43: (=) | B43: RESULTADO LÍQUIDO | C43: =C35+C40 | D43: =D35+D40 | E43: =E35+E40 | F43: =F35+F40 | G43: =G35+G40 | H43: =H35+H40 | I43: =I35+I40 | J43: =J35+J40 | ... N43: =N35+N40 | O43: =SUM(C43:N43)
A45: (%) | B45: MARGEM LÍQUIDA | C45: =IFERROR(C43/C11,0) | D45: =IFERROR(D43/D11,0) | E45: =IFERROR(E43/E11,0) | F45: =IFERROR(F43/F11,0) | G45: =IFERROR(G43/G11,0) | H45: =IFERROR(H43/H11,0) | I45: =IFERROR(I43/I11,0) | J45: =IFERROR(J43/J11,0) | ... O45: =IFERROR(O43/O11,0)

Sheet Categorias
A1: SyncSheet — Sistema de Gestão Financeira
A2: Categorias
A3: Plano de contas — Receitas e Despesas
A4: Código | B4: Categoria de Receita
A5: R01 | B5: Vendas de Produtos
A6: R02 | B6: Vendas de Serviços
A7: R03 | B7: Cursos e Infoprodutos
A8: R04 | B8: Assinaturas / Recorrência
A9: R05 | B9: Receitas Financeiras
A10: R06 | B10: Outras Receitas
A14: Código | B14: Categoria de Despesa
A15: D01 | B15: CMV (Custo da Mercadoria Vendida)
A16: D02 | B16: Custo de Serviço
A17: D03 | B17: Salários e Encargos
A18: D04 | B18: Aluguel
... A26: D12 | B26: Outras Despesas
